tt_util/__init__.py
tt_util/aes_util.py
tt_util/alioss_util.py
tt_util/check_domain.py
tt_util/config_util.py
tt_util/docker_util.py
tt_util/exec_shell.py
tt_util/oauth2.py
tt_util/pyinitlog_util.py
tt_util/pykafka_util.py
tt_util/pyresp.py
tt_util/qiniu_util.py
tt_util/ssh_util.py
tt_util/svn_util.py
tt_util/uuid_util.py
tt_util/yaml_util.py
tt_util-1.4.0.dist-info/LICENSE
tt_util-1.4.0.dist-info/METADATA
tt_util-1.4.0.dist-info/WHEEL
tt_util-1.4.0.dist-info/top_level.txt
tt_util-1.4.0.dist-info/zip-safe
tt_util-1.4.0.dist-info/RECORD
