Metadata-Version: 2.1
Name: tt_util
Version: 1.4.0
Summary: buyfakett自用的工具包
Home-page: https://github.com/buyfakett
Author: buyfakett
Author-email: buyfakett@vip.qq.com
License: MIT
Requires-Python: >=3.6
License-File: LICENSE
Requires-Dist: colorlog
Requires-Dist: dnspython
Requires-Dist: pyyaml
Requires-Dist: paramiko
Requires-Dist: pycryptodome
Requires-Dist: qiniu
Requires-Dist: docker
Requires-Dist: oss2
Requires-Dist: confluent-kafka
